brainai/__init__.py
brainai/_openai_scripts.py
brainai/api_requestor.py
brainai/brainai_object.py
brainai/brainai_response.py
brainai/cli.py
brainai/embeddings_utils.py
brainai/error.py
brainai/object_classes.py
brainai/py.typed
brainai/upload_progress.py
brainai/util.py
brainai/validators.py
brainai/version.py
brainai/wandb_logger.py
brainai/api_resources/__init__.py
brainai/api_resources/audio.py
brainai/api_resources/brainos_completion.py
brainai/api_resources/chat_completion.py
brainai/api_resources/completion.py
brainai/api_resources/customer.py
brainai/api_resources/deployment.py
brainai/api_resources/edit.py
brainai/api_resources/embedding.py
brainai/api_resources/engine.py
brainai/api_resources/error_object.py
brainai/api_resources/file.py
brainai/api_resources/fine_tune.py
brainai/api_resources/fine_tuning.py
brainai/api_resources/image.py
brainai/api_resources/model.py
brainai/api_resources/moderation.py
brainai/api_resources/abstract/__init__.py
brainai/api_resources/abstract/api_resource.py
brainai/api_resources/abstract/createable_api_resource.py
brainai/api_resources/abstract/deletable_api_resource.py
brainai/api_resources/abstract/engine_api_resource.py
brainai/api_resources/abstract/listable_api_resource.py
brainai/api_resources/abstract/nested_resource_class_methods.py
brainai/api_resources/abstract/paginatable_api_resource.py
brainai/api_resources/abstract/updateable_api_resource.py
brainai/api_resources/experimental/__init__.py
brainai/api_resources/experimental/completion_config.py
brainai/datalib/__init__.py
brainai/datalib/common.py
brainai/datalib/numpy_helper.py
brainai/datalib/pandas_helper.py
brainai/test/__init__.py
brainai/test/brainos_test.py
brainai/test/models_test.py
brainai/test/other_test.py
brainai/tests/__init__.py
brainai/tests/test_api_requestor.py
brainai/tests/test_endpoints.py
brainai/tests/test_exceptions.py
brainai/tests/test_file_cli.py
brainai/tests/test_long_examples_validator.py
brainai/tests/test_url_composition.py
pyBrainai-1.4.1.2.dist-info/LICENSE
pyBrainai-1.4.1.2.dist-info/METADATA
pyBrainai-1.4.1.2.dist-info/WHEEL
pyBrainai-1.4.1.2.dist-info/top_level.txt
pyBrainai-1.4.1.2.dist-info/RECORD
